HeteroSymNN/__init__.py
HeteroSymNN/types.py
HeteroSymNN/API/__init__.py
HeteroSymNN/API/wrappers.py
HeteroSymNN/Backend/__init__.py
HeteroSymNN/Backend/hardware.py
HeteroSymNN/Backend/tuner.py
HeteroSymNN/Core/__init__.py
HeteroSymNN/Core/initializers.py
HeteroSymNN/Core/losses.py
HeteroSymNN/Core/optimizers.py
HeteroSymNN/Core/utils.py
HeteroSymNN/Core/Nets/__init__.py
HeteroSymNN/Core/Nets/layers.py
HeteroSymNN/Core/Nets/neural_nets.py
HeteroSymNN/JIT/__init__.py
HeteroSymNN/JIT/compiler.py
HeteroSymNN/JIT/templates.py
heterosymnn-0.2.0.dist-info/licenses/LICENSE
heterosymnn-0.2.0.dist-info/METADATA
heterosymnn-0.2.0.dist-info/WHEEL
heterosymnn-0.2.0.dist-info/top_level.txt
heterosymnn-0.2.0.dist-info/RECORD
