Metadata-Version: 2.4
Name: HeteroSymNN
Version: 0.2.0
Author: Dilosch03
Requires-Python: >=3.10
License-File: LICENSE
Requires-Dist: numpy<2.3,>=2.0
Requires-Dist: sympy~=1.14
Requires-Dist: platformdirs~=4.5
Provides-Extra: gpu
Requires-Dist: cupy~=13.6; extra == "gpu"
Dynamic: author
Dynamic: license-file
Dynamic: provides-extra
Dynamic: requires-dist
Dynamic: requires-python
